{
  "title": "agreeing with someone",
  "description": "Practice agreeing and adding a positive comment.",
  "languageId": "",
  "difficultyLevel": "BEGINNER",
  "estimatedDuration": 5,
  "status": "DRAFT",
  "category": "opinions",
  "content": {
    "lesson_metadata": {
      "lesson_id": "badge_001-L02",
      "generation_timestamp": "2026-05-02T13:34:48Z",
      "version": "2.0.0",
      "created_by": "pipeline",
      "level_config": {
        "level_code": "A1",
        "level_name": "Beginner",
        "level_description": "Build basic everyday phrases for simple, familiar topics.",
        "cefr_equivalent": "A1",
        "available_levels": [
          "A0",
          "A1",
          "A2",
          "B1",
          "B2",
          "C1",
          "C2"
        ]
      },
      "theme_config": {
        "theme_id": "OPINIONS",
        "theme_code": "OPINIONS",
        "theme_name": "Opinions",
        "theme_description": "Express agreement and share simple opinions about places.",
        "available_themes": [
          {
            "code": "ESS",
            "name": "Essentials"
          },
          {
            "code": "TRV",
            "name": "Travel"
          }
        ]
      },
      "unit_config": {
        "unit_id": "2.1a",
        "unit_number": 2,
        "subunit_number": 1,
        "variant": "a",
        "unit_name": "Where I Live",
        "unit_description": "Talk about the places where you live, study, and spend time, and say what you like about them.",
        "total_lessons_in_unit": 15,
        "unit_difficulty": 2,
        "estimated_completion_time_minutes": 75
      },
      "lesson_config": {
        "lesson_number": 122,
        "lesson_type": "teaching",
        "lesson_name": "agreeing with someone",
        "lesson_description": "Practice agreeing and adding a positive comment.",
        "estimated_duration_minutes": 5,
        "difficulty_within_unit": 2,
        "prerequisites": [
          "badge_001-L01"
        ],
        "learning_objectives": [
          "Use 'I agree' to show you share someone's opinion.",
          "Combine agreement with a positive comment using 'It is a + adjective + noun'.",
          "Recognize four opinion words: lovely, pleasant, amazing, opinion."
        ],
        "target_interactions": "15-20",
        "micro_flow_version": "2.0"
      },
      "order": 122
    },
    "lesson_structure": {
      "module_order_config": {
        "ordering_strategy": "standard",
        "selected_order": [
          "module_1_core_vocabulary",
          "module_2_functional_grammar",
          "module_3_sentence_building",
          "module_dialogue_practice",
          "module_sprint_exercises"
        ]
      },
      "modules": {
        "module_1_core_vocabulary": {
          "module_id": "module_1",
          "module_name": "Vocabulary Anchor",
          "module_code": "VOCAB",
          "position_in_lesson": 1,
          "enabled": true,
          "required": true,
          "estimated_duration_seconds": 60,
          "title_source": "Key phrases",
          "title_target": "[TRANSLATE]",
          "module_type": "Vocabulary",
          "vocabulary_items": [
            {
              "vocab_id": "core_2",
              "phrase_id": 1,
              "source_text": "I agree. It is a nice city.",
              "target_text": "[TRANSLATE]",
              "part_of_speech": "verb",
              "frequency_rank": 1,
              "difficulty": 1,
              "context": {
                "usage_context": "opinion",
                "formality_level": "neutral",
                "time_of_day": "any",
                "relationship": "any"
              },
              "linguistic_info": {
                "tooltip_source": "Use this to agree with someone and add a positive comment about a place.",
                "tooltip_target": "[TRANSLATE]",
                "pronunciation_guide": "[GENERATE_FOR_TARGET]"
              },
              "media": {
                "image_url": "",
                "audio_normal": "[GENERATE]",
                "audio_slow": "[GENERATE]"
              },
              "exercises": {
                "exercise_selection_strategy": "sequential",
                "selected_exercises": []
              }
            },
            {
              "vocab_id": "rel_2_001",
              "phrase_id": 2,
              "source_text": "lovely",
              "target_text": "[TRANSLATE]",
              "part_of_speech": "adjective",
              "frequency_rank": 2,
              "difficulty": 1,
              "context": {},
              "linguistic_info": {
                "tooltip_source": "Very nice or pleasant.",
                "tooltip_target": "[TRANSLATE]",
                "pronunciation_guide": "[GENERATE_FOR_TARGET]"
              },
              "media": {
                "image_url": "",
                "audio_normal": "[GENERATE]",
                "audio_slow": "[GENERATE]"
              },
              "exercises": {
                "exercise_selection_strategy": "sequential",
                "selected_exercises": []
              }
            },
            {
              "vocab_id": "rel_2_002",
              "phrase_id": 3,
              "source_text": "pleasant",
              "target_text": "[TRANSLATE]",
              "part_of_speech": "adjective",
              "frequency_rank": 3,
              "difficulty": 1,
              "context": {},
              "linguistic_info": {
                "tooltip_source": "Friendly and enjoyable.",
                "tooltip_target": "[TRANSLATE]",
                "pronunciation_guide": "[GENERATE_FOR_TARGET]"
              },
              "media": {
                "image_url": "",
                "audio_normal": "[GENERATE]",
                "audio_slow": "[GENERATE]"
              },
              "exercises": {
                "exercise_selection_strategy": "sequential",
                "selected_exercises": []
              }
            },
            {
              "vocab_id": "rel_2_003",
              "phrase_id": 4,
              "source_text": "amazing",
              "target_text": "[TRANSLATE]",
              "part_of_speech": "adjective",
              "frequency_rank": 4,
              "difficulty": 1,
              "context": {},
              "linguistic_info": {
                "tooltip_source": "Very impressive or surprising.",
                "tooltip_target": "[TRANSLATE]",
                "pronunciation_guide": "[GENERATE_FOR_TARGET]"
              },
              "media": {
                "image_url": "",
                "audio_normal": "[GENERATE]",
                "audio_slow": "[GENERATE]"
              },
              "exercises": {
                "exercise_selection_strategy": "sequential",
                "selected_exercises": []
              }
            },
            {
              "vocab_id": "rel_2_004",
              "phrase_id": 5,
              "source_text": "opinion",
              "target_text": "[TRANSLATE]",
              "part_of_speech": "noun",
              "frequency_rank": 5,
              "difficulty": 1,
              "context": {},
              "linguistic_info": {
                "tooltip_source": "What a person thinks about something.",
                "tooltip_target": "[TRANSLATE]",
                "pronunciation_guide": "[GENERATE_FOR_TARGET]"
              },
              "media": {
                "image_url": "",
                "audio_normal": "[GENERATE]",
                "audio_slow": "[GENERATE]"
              },
              "exercises": {
                "exercise_selection_strategy": "sequential",
                "selected_exercises": []
              }
            }
          ],
          "vocabulary_anchor_listen_repeat": {
            "prompt_source": "Listen and repeat the core phrase.",
            "prompt_target": "[TRANSLATE]",
            "audio_stimulus": {
              "audio_file": "[GENERATE]",
              "play_on_load": true,
              "text_to_speak_target": "I agree. It is a nice city."
            },
            "show_text_after_play": true
          },
          "vocabulary_anchor_quick_match": {
            "prompt_source": "Connect each word to its meaning or image.",
            "prompt_target": "[TRANSLATE]",
            "match_pairs": [
              {
                "pair_id": "qm_2_001",
                "word_id": "rel_2_001",
                "correct_key": "rel_2_001_correct"
              },
              {
                "pair_id": "qm_2_002",
                "word_id": "rel_2_002",
                "correct_key": "rel_2_002_correct"
              },
              {
                "pair_id": "qm_2_003",
                "word_id": "rel_2_003",
                "correct_key": "rel_2_003_correct"
              },
              {
                "pair_id": "qm_2_004",
                "word_id": "rel_2_004",
                "correct_key": "rel_2_004_correct"
              }
            ],
            "options_display": "shuffle"
          }
        },
        "module_2_functional_grammar": {
          "module_id": "module_2",
          "module_name": "Grammar Engine",
          "module_code": "GRAMMAR",
          "position_in_lesson": 2,
          "enabled": true,
          "required": true,
          "estimated_duration_seconds": 45,
          "title_source": "Grammar tip",
          "title_target": "[TRANSLATE]",
          "module_type": "Grammar",
          "grammar_points": [
            {
              "grammar_id": "gram_2",
              "concept_source": "Agreeing and adding a positive comment",
              "concept_target": "[TRANSLATE]",
              "explanation_source": "Use 'I agree' to show you share someone's view, then add a sentence like 'It is a + adjective + noun' to give a reason.",
              "explanation_target": "[TRANSLATE]",
              "focus_type": "variations",
              "examples": [
                {
                  "example_id": "ex_2_001",
                  "text_source": "I agree. It is a lovely town.",
                  "text_target": "[TRANSLATE]",
                  "register": "neutral",
                  "usage_note_source": "Use 'lovely' instead of 'nice' for a warmer feeling.",
                  "usage_note_target": "[TRANSLATE]",
                  "audio_normal": "[GENERATE]",
                  "audio_slow": "[GENERATE]"
                },
                {
                  "example_id": "ex_2_002",
                  "text_source": "Yes, I agree. It is amazing.",
                  "text_target": "[TRANSLATE]",
                  "register": "informal",
                  "usage_note_source": "Add 'Yes' before 'I agree' to sound more casual.",
                  "usage_note_target": "[TRANSLATE]",
                  "audio_normal": "[GENERATE]",
                  "audio_slow": "[GENERATE]"
                }
              ]
            }
          ],
          "grammar_engine_modifiers": [
            {
              "modifier_id": "mod_2_001",
              "modifier_source": "totally",
              "modifier_target": "[TRANSLATE]",
              "example_source": "I totally agree. It is a nice city.",
              "example_target": "[TRANSLATE]",
              "explanation_source": "Use 'totally' before 'agree' to show very strong agreement.",
              "explanation_target": "[TRANSLATE]",
              "audio_normal": "[GENERATE]",
              "audio_slow": "[GENERATE]"
            },
            {
              "modifier_id": "mod_2_002",
              "modifier_source": "very",
              "modifier_target": "[TRANSLATE]",
              "example_source": "I agree. It is a very nice city.",
              "example_target": "[TRANSLATE]",
              "explanation_source": "Use 'very' before an adjective to make it stronger.",
              "explanation_target": "[TRANSLATE]",
              "audio_normal": "[GENERATE]",
              "audio_slow": "[GENERATE]"
            }
          ]
        },
        "module_3_sentence_building": {
          "module_id": "module_3",
          "module_name": "Sentence Building",
          "module_code": "SENTENCE",
          "position_in_lesson": 3,
          "enabled": true,
          "required": true,
          "estimated_duration_seconds": 60,
          "title_source": "Build sentences",
          "title_target": "[TRANSLATE]",
          "module_type": "SentenceBuilding",
          "exercises": [
            {
              "exercise_id": "ex_sb_2_1",
              "target_sentence_source": "I agree. It is a nice city.",
              "target_sentence_target": "[TRANSLATE]",
              "punctuation_mode": "auto_fit",
              "word_tiles": [
                {
                  "word_id": "w1",
                  "word_source": "I",
                  "word_target": "[TRANSLATE]",
                  "correct_position": 1
                },
                {
                  "word_id": "w2",
                  "word_source": "agree",
                  "word_target": "[TRANSLATE]",
                  "correct_position": 2
                },
                {
                  "word_id": "w3",
                  "word_source": "It",
                  "word_target": "[TRANSLATE]",
                  "correct_position": 3
                },
                {
                  "word_id": "w4",
                  "word_source": "is",
                  "word_target": "[TRANSLATE]",
                  "correct_position": 4
                },
                {
                  "word_id": "w5",
                  "word_source": "a",
                  "word_target": "[TRANSLATE]",
                  "correct_position": 5
                },
                {
                  "word_id": "w6",
                  "word_source": "nice",
                  "word_target": "[TRANSLATE]",
                  "correct_position": 6
                },
                {
                  "word_id": "w7",
                  "word_source": "city",
                  "word_target": "[TRANSLATE]",
                  "correct_position": 7
                }
              ],
              "hints": "Two short sentences: agree first, then a positive comment.",
              "exercise_type": "Drag-and-Drop Sentence Builder",
              "prompt_source": "Put the words in the correct order:",
              "prompt_target": "[TRANSLATE]",
              "hints_source": "Two short sentences: agree first, then a positive comment.",
              "hints_target": "[TRANSLATE]"
            },
            {
              "exercise_id": "ex_sb_2_2",
              "target_sentence_source": "It is a lovely town.",
              "target_sentence_target": "[TRANSLATE]",
              "punctuation_mode": "auto_fit",
              "word_tiles": [
                {
                  "word_id": "w1",
                  "word_source": "It",
                  "word_target": "[TRANSLATE]",
                  "correct_position": 1
                },
                {
                  "word_id": "w2",
                  "word_source": "is",
                  "word_target": "[TRANSLATE]",
                  "correct_position": 2
                },
                {
                  "word_id": "w3",
                  "word_source": "a",
                  "word_target": "[TRANSLATE]",
                  "correct_position": 3
                },
                {
                  "word_id": "w4",
                  "word_source": "lovely",
                  "word_target": "[TRANSLATE]",
                  "correct_position": 4
                },
                {
                  "word_id": "w5",
                  "word_source": "town",
                  "word_target": "[TRANSLATE]",
                  "correct_position": 5
                }
              ],
              "hints": "Use 'It is a' before the adjective and noun.",
              "exercise_type": "Drag-and-Drop Sentence Builder",
              "prompt_source": "Put the words in the correct order:",
              "prompt_target": "[TRANSLATE]",
              "hints_source": "Use 'It is a' before the adjective and noun.",
              "hints_target": "[TRANSLATE]"
            }
          ]
        },
        "module_dialogue_practice": {
          "module_id": "module_dialogue_practice",
          "module_name": "Dialogue Practice",
          "module_code": "DIALOGUE",
          "position_in_lesson": 4,
          "enabled": true,
          "required": true,
          "estimated_duration_seconds": 90,
          "title_source": "Conversation",
          "title_target": "[TRANSLATE]",
          "module_type": "Conversations",
          "setting_source": "Two friends comparing opinions about a place",
          "setting_target": "[TRANSLATE]",
          "context_source": "Sharing positive views about a city they live in",
          "context_target": "[TRANSLATE]",
          "setting": "Two friends comparing opinions about a place",
          "context": "Sharing positive views about a city they live in",
          "dialogue": [
            {
              "turn_id": "turn_001",
              "turn_number": 1,
              "speaker": "PARTNER",
              "text_source": "I really like this place. It feels welcoming.",
              "text_target": "[TRANSLATE]",
              "audio_file": "[GENERATE]",
              "practice_mode": "listen_and_repeat",
              "audio_normal": "[GENERATE]",
              "audio_slow": "[GENERATE]"
            },
            {
              "turn_id": "turn_002",
              "turn_number": 2,
              "speaker": "YOU",
              "text_source": "I agree. It is a nice city.",
              "text_target": "[TRANSLATE]",
              "audio_file": "[GENERATE]",
              "practice_mode": "speak_along",
              "audio_normal": "[GENERATE]",
              "audio_slow": "[GENERATE]"
            },
            {
              "turn_id": "turn_003",
              "turn_number": 3,
              "speaker": "PARTNER",
              "text_source": "The streets are clean too.",
              "text_target": "[TRANSLATE]",
              "audio_file": "[GENERATE]",
              "practice_mode": "listen_and_repeat",
              "audio_normal": "[GENERATE]",
              "audio_slow": "[GENERATE]"
            },
            {
              "turn_id": "turn_004",
              "turn_number": 4,
              "speaker": "YOU",
              "text_source": "Yes, and the parks are lovely.",
              "text_target": "[TRANSLATE]",
              "audio_file": "[GENERATE]",
              "practice_mode": "speak_along",
              "audio_normal": "[GENERATE]",
              "audio_slow": "[GENERATE]"
            },
            {
              "turn_id": "turn_005",
              "turn_number": 5,
              "speaker": "PARTNER",
              "text_source": "I'm glad we settled here.",
              "text_target": "[TRANSLATE]",
              "audio_file": "[GENERATE]",
              "practice_mode": "listen_and_repeat",
              "audio_normal": "[GENERATE]",
              "audio_slow": "[GENERATE]"
            }
          ]
        },
        "module_sprint_exercises": {
          "position_in_lesson": 5,
          "enabled": true,
          "required": true,
          "estimated_duration_seconds": 120,
          "title_source": "Quick practice",
          "title_target": "[TRANSLATE]",
          "randomize_order": true,
          "exercises": [
            {
              "exercise_id": "ex_sp_audio_text",
              "exercise_type": "Audio-to-Text Matching",
              "prompt_source": "Select the phrase you hear:",
              "prompt_target": "[TRANSLATE]",
              "audio_stimulus": {
                "audio_file": "[GENERATE]",
                "play_on_load": false
              },
              "text_options": [
                "I agree. It is a nice city.",
                "I agree. It is a lovely town.",
                "It is amazing here."
              ],
              "text_options_source": [
                "I agree. It is a nice city.",
                "I agree. It is a lovely town.",
                "It is amazing here."
              ],
              "text_options_target": [
                "[TRANSLATE]",
                "[TRANSLATE]",
                "[TRANSLATE]"
              ],
              "correct_answer": "I agree. It is a nice city.",
              "correct_answer_source": "I agree. It is a nice city.",
              "correct_answer_target": "[TRANSLATE]",
              "scoring": {
                "points_correct": 10,
                "points_incorrect": 0
              }
            },
            {
              "exercise_id": "ex_sp_quick_fire",
              "exercise_type": "Listen and Respond (Quick Fire)",
              "prompt_source": "Listen and respond out loud:",
              "prompt_target": "[TRANSLATE]",
              "audio_stimulus": {
                "audio_file": "[GENERATE]",
                "play_on_load": true,
                "text_to_speak_target": "Don't you love this city?"
              },
              "prompt": "Don't you love this city?",
              "prompt_text_source": "Don't you love this city?",
              "prompt_text_target": "[TRANSLATE]",
              "response": {
                "mode": "speech",
                "acceptable_responses": [
                  "I agree. It is a nice city.",
                  "Yes, I agree."
                ],
                "acceptable_responses_source": [
                  "I agree. It is a nice city.",
                  "Yes, I agree."
                ],
                "acceptable_responses_target": [
                  "[TRANSLATE]",
                  "[TRANSLATE]"
                ],
                "time_limit_seconds": 8
              },
              "scoring": {
                "points_correct": 10,
                "points_incorrect": 0
              }
            },
            {
              "exercise_id": "ex_sp_sentence_open",
              "exercise_type": "Sentence Completion (Open)",
              "prompt_source": "Finish in your own words:",
              "prompt_target": "[TRANSLATE]",
              "prompt": "I agree. It is a ___",
              "prompt_text_source": "I agree. It is a ___",
              "prompt_text_target": "[TRANSLATE]",
              "expected_response": "an adjective + noun describing a place, e.g. 'nice city' or 'lovely town'",
              "expected_response_source": "an adjective + noun describing a place, e.g. 'nice city' or 'lovely town'",
              "expected_response_target": "[TRANSLATE]",
              "scoring_criteria": "Accept any positive adjective followed by a place noun.",
              "scoring_criteria_source": "Accept any positive adjective followed by a place noun.",
              "scoring_criteria_target": "[TRANSLATE]",
              "scoring": {
                "points_correct": 10,
                "points_incorrect": 0
              }
            },
            {
              "exercise_id": "ex_sp_fill_dialogue",
              "exercise_type": "Fill-in-the-Dialogue (Speaking)",
              "prompt_source": "Speak your line:",
              "prompt_target": "[TRANSLATE]",
              "dialogue_context": "A friend compliments your city.",
              "dialogue_context_source": "A friend compliments your city.",
              "dialogue_context_target": "[TRANSLATE]",
              "turns": [
                {
                  "turn_number": 1,
                  "speaker": "PARTNER",
                  "text_source": "Your city looks beautiful.",
                  "text_target": "[TRANSLATE]",
                  "audio_file": "[GENERATE]",
                  "text_to_speak_target": "Your city looks beautiful."
                },
                {
                  "turn_number": 2,
                  "speaker": "YOU",
                  "text_source": "I agree. It is a nice city.",
                  "expected_response": "I agree. It is a nice city.",
                  "expected_response_source": "I agree. It is a nice city.",
                  "expected_response_target": "[TRANSLATE]",
                  "acceptable_responses": [
                    "I agree. It is a nice city.",
                    "Yes, I agree."
                  ],
                  "acceptable_responses_source": [
                    "I agree. It is a nice city.",
                    "Yes, I agree."
                  ],
                  "acceptable_responses_target": [
                    "[TRANSLATE]",
                    "[TRANSLATE]"
                  ]
                }
              ],
              "scoring": {
                "points_correct": 15,
                "points_incorrect": 0
              }
            },
            {
              "exercise_id": "ex_sp_match_game",
              "exercise_type": "Flashcard Matching Game",
              "prompt_source": "Match pairs:",
              "prompt_target": "[TRANSLATE]",
              "pairs": [
                {
                  "pair_id": "mg_2_001",
                  "item_a": "lovely",
                  "item_b": "very nice",
                  "type": "synonym"
                },
                {
                  "pair_id": "mg_2_002",
                  "item_a": "agree",
                  "item_b": "share a view",
                  "type": "word_meaning"
                },
                {
                  "pair_id": "mg_2_003",
                  "item_a": "amazing",
                  "item_b": "very impressive",
                  "type": "synonym"
                },
                {
                  "pair_id": "mg_2_004",
                  "item_a": "opinion",
                  "item_b": "what you think",
                  "type": "word_meaning"
                }
              ],
              "scoring": {
                "points_correct": 10,
                "points_incorrect": 0
              }
            }
          ],
          "module_id": "module_sprint_exercises",
          "module_name": "Sprint & review",
          "module_code": "SPRINT",
          "module_type": "Review"
        }
      }
    },
    "translation_metadata": {
      "source_language": "en",
      "target_language": "RUNTIME_SELECTED",
      "translatable_field_patterns": [
        "**_target"
      ],
      "audio_generation_patterns": [
        "[GENERATE]",
        "[GENERATE_FOR_TARGET]"
      ]
    }
  },
  "metadata": {
    "lessonType": "malegado",
    "uploadSchema": "modules_canonical_v1",
    "convertedFrom": "new_structure_v4_phases",
    "sourcePath": "/home/metuge/Dev/submissions/malegado_new_structure/Dialogues/dialogue 9/lesson_02.json",
    "sourceLessonId": "badge_001-L02"
  }
}
