{
  "title": "saying you are tired",
  "description": "Tell someone how tired you feel.",
  "languageId": "68629d0d457e13090cb4194d",
  "difficultyLevel": "BEGINNER",
  "estimatedDuration": 5,
  "status": "PUBLISHED",
  "category": "health",
  "content": {
    "lesson_metadata": {
      "lesson_id": "badge_nap_future_001-L12",
      "generation_timestamp": "2026-05-04T07:05:55Z",
      "version": "2.0.0",
      "created_by": "pipeline",
      "level_config": {
        "level_code": "A2",
        "level_name": "Elementary",
        "level_description": "Builds simple sentences about everyday topics with growing confidence.",
        "cefr_equivalent": "A2",
        "available_levels": [
          "A0",
          "A1",
          "A2",
          "B1",
          "B2",
          "C1",
          "C2"
        ]
      },
      "theme_config": {
        "theme_id": "HEALTH",
        "theme_code": "HEALTH",
        "theme_name": "Health",
        "theme_description": "Talking about how your body and energy feel day to day.",
        "available_themes": [
          {
            "code": "ESS",
            "name": "Essentials"
          },
          {
            "code": "TRV",
            "name": "Travel"
          }
        ]
      },
      "unit_config": {
        "unit_id": "1.1b",
        "unit_number": 1,
        "subunit_number": 1,
        "variant": "b",
        "unit_name": "Rest and Plans",
        "unit_description": "A short badge for talking about naps, evening plans, and giving simple advice around the home.",
        "total_lessons_in_unit": 15,
        "unit_difficulty": 3,
        "estimated_completion_time_minutes": 75
      },
      "lesson_config": {
        "lesson_number": 492,
        "lesson_type": "teaching",
        "lesson_name": "saying you are tired",
        "lesson_description": "Practice describing how tired you feel using 'I am very ___.'",
        "estimated_duration_minutes": 5,
        "difficulty_within_unit": 12,
        "prerequisites": [
          "badge_nap_future_001-L01",
          "badge_nap_future_001-L02",
          "badge_nap_future_001-L03",
          "badge_nap_future_001-L04",
          "badge_nap_future_001-L05",
          "badge_nap_future_001-L06",
          "badge_nap_future_001-L07",
          "badge_nap_future_001-L08",
          "badge_nap_future_001-L09",
          "badge_nap_future_001-L10",
          "badge_nap_future_001-L11"
        ],
        "learning_objectives": [
          "Describe a feeling using 'I am + adverb + adjective.'",
          "Vary the strength of the feeling with 'very', 'so', and 'a little'.",
          "Recognise simple tiredness vocabulary (exhausted, sleepy, energy, weary)."
        ],
        "target_interactions": "15-20",
        "micro_flow_version": "2.0"
      },
      "order": 492
    },
    "lesson_structure": {
      "module_order_config": {
        "ordering_strategy": "standard",
        "selected_order": [
          "module_1_core_vocabulary",
          "module_2_functional_grammar",
          "module_3_sentence_building",
          "module_dialogue_practice",
          "module_sprint_exercises"
        ]
      },
      "modules": {
        "module_1_core_vocabulary": {
          "module_id": "module_1",
          "module_name": "Vocabulary Anchor",
          "module_code": "VOCAB",
          "position_in_lesson": 1,
          "enabled": true,
          "required": true,
          "estimated_duration_seconds": 60,
          "title_source": "Key phrases",
          "title_target": "[TRANSLATE]",
          "module_type": "Vocabulary",
          "vocabulary_items": [
            {
              "vocab_id": "core_12",
              "phrase_id": 1,
              "source_text": "I am very tired.",
              "target_text": "[TRANSLATE]",
              "part_of_speech": "phrase",
              "frequency_rank": 1,
              "difficulty": 1,
              "context": {
                "usage_context": "self_description",
                "formality_level": "neutral",
                "time_of_day": "any",
                "relationship": "any"
              },
              "linguistic_info": {
                "tooltip_source": "A simple, direct way to tell someone you have very low energy or need rest.",
                "tooltip_target": "[TRANSLATE]",
                "pronunciation_guide": "[GENERATE_FOR_TARGET]"
              },
              "media": {
                "image_url": "",
                "audio_normal": "[GENERATE]",
                "audio_slow": "[GENERATE]"
              },
              "exercises": {
                "exercise_selection_strategy": "sequential",
                "selected_exercises": []
              }
            },
            {
              "vocab_id": "rel_12_001",
              "phrase_id": 2,
              "source_text": "exhausted",
              "target_text": "[TRANSLATE]",
              "part_of_speech": "adjective",
              "frequency_rank": 2,
              "difficulty": 1,
              "context": {},
              "linguistic_info": {
                "tooltip_source": "Extremely tired, with no energy left.",
                "tooltip_target": "[TRANSLATE]",
                "pronunciation_guide": "[GENERATE_FOR_TARGET]"
              },
              "media": {
                "image_url": "",
                "audio_normal": "[GENERATE]",
                "audio_slow": "[GENERATE]"
              },
              "exercises": {
                "exercise_selection_strategy": "sequential",
                "selected_exercises": []
              }
            },
            {
              "vocab_id": "rel_12_002",
              "phrase_id": 3,
              "source_text": "sleepy",
              "target_text": "[TRANSLATE]",
              "part_of_speech": "adjective",
              "frequency_rank": 3,
              "difficulty": 1,
              "context": {},
              "linguistic_info": {
                "tooltip_source": "Feeling that you want to go to sleep.",
                "tooltip_target": "[TRANSLATE]",
                "pronunciation_guide": "[GENERATE_FOR_TARGET]"
              },
              "media": {
                "image_url": "",
                "audio_normal": "[GENERATE]",
                "audio_slow": "[GENERATE]"
              },
              "exercises": {
                "exercise_selection_strategy": "sequential",
                "selected_exercises": []
              }
            },
            {
              "vocab_id": "rel_12_003",
              "phrase_id": 4,
              "source_text": "energy",
              "target_text": "[TRANSLATE]",
              "part_of_speech": "noun",
              "frequency_rank": 4,
              "difficulty": 1,
              "context": {},
              "linguistic_info": {
                "tooltip_source": "The strength to do things; how much you can do before you feel tired.",
                "tooltip_target": "[TRANSLATE]",
                "pronunciation_guide": "[GENERATE_FOR_TARGET]"
              },
              "media": {
                "image_url": "",
                "audio_normal": "[GENERATE]",
                "audio_slow": "[GENERATE]"
              },
              "exercises": {
                "exercise_selection_strategy": "sequential",
                "selected_exercises": []
              }
            },
            {
              "vocab_id": "rel_12_004",
              "phrase_id": 5,
              "source_text": "weary",
              "target_text": "[TRANSLATE]",
              "part_of_speech": "adjective",
              "frequency_rank": 5,
              "difficulty": 1,
              "context": {},
              "linguistic_info": {
                "tooltip_source": "Very tired, often after a lot of effort or worry.",
                "tooltip_target": "[TRANSLATE]",
                "pronunciation_guide": "[GENERATE_FOR_TARGET]"
              },
              "media": {
                "image_url": "",
                "audio_normal": "[GENERATE]",
                "audio_slow": "[GENERATE]"
              },
              "exercises": {
                "exercise_selection_strategy": "sequential",
                "selected_exercises": []
              }
            }
          ],
          "vocabulary_anchor_listen_repeat": {
            "prompt_source": "Listen and repeat the core phrase.",
            "prompt_target": "[TRANSLATE]",
            "audio_stimulus": {
              "audio_file": "[GENERATE]",
              "play_on_load": true,
              "text_to_speak_target": "I am very tired."
            },
            "show_text_after_play": true
          },
          "vocabulary_anchor_quick_match": {
            "prompt_source": "Connect each word to its meaning or image.",
            "prompt_target": "[TRANSLATE]",
            "match_pairs": [
              {
                "word_id": "rel_12_001",
                "correct_key": "rel_12_001_correct"
              },
              {
                "word_id": "rel_12_002",
                "correct_key": "rel_12_002_correct"
              },
              {
                "word_id": "rel_12_003",
                "correct_key": "rel_12_003_correct"
              },
              {
                "word_id": "rel_12_004",
                "correct_key": "rel_12_004_correct"
              }
            ],
            "options_display": "shuffle"
          }
        },
        "module_2_functional_grammar": {
          "module_id": "module_2",
          "module_name": "Grammar Engine",
          "module_code": "GRAMMAR",
          "position_in_lesson": 2,
          "enabled": true,
          "required": true,
          "estimated_duration_seconds": 45,
          "title_source": "Grammar tip",
          "title_target": "[TRANSLATE]",
          "module_type": "Grammar",
          "grammar_points": [
            {
              "grammar_id": "gram_12",
              "concept_source": "Be + intensifier + adjective",
              "concept_target": "[TRANSLATE]",
              "explanation_source": "Use 'I am + adverb + adjective' to describe how you feel. The adverb (very, so, a little) shows how strong the feeling is.",
              "explanation_target": "[TRANSLATE]",
              "focus_type": "variations",
              "examples": [
                {
                  "example_id": "ex_12_001",
                  "text_source": "I'm really tired.",
                  "text_target": "[TRANSLATE]",
                  "register": "informal",
                  "usage_note_source": "Casual contracted form, used with friends and family.",
                  "usage_note_target": "[TRANSLATE]",
                  "audio_normal": "[GENERATE]",
                  "audio_slow": "[GENERATE]"
                },
                {
                  "example_id": "ex_12_002",
                  "text_source": "I am extremely tired.",
                  "text_target": "[TRANSLATE]",
                  "register": "formal",
                  "usage_note_source": "'Extremely' is a slightly more formal way to strengthen the adjective.",
                  "usage_note_target": "[TRANSLATE]",
                  "audio_normal": "[GENERATE]",
                  "audio_slow": "[GENERATE]"
                }
              ]
            }
          ],
          "grammar_engine_modifiers": [
            {
              "modifier_id": "mod_12_001",
              "modifier_source": "so",
              "modifier_target": "[TRANSLATE]",
              "example_source": "I am so tired.",
              "example_target": "[TRANSLATE]",
              "explanation_source": "Replace 'very' with 'so' for an even stronger feeling.",
              "explanation_target": "[TRANSLATE]",
              "audio_normal": "[GENERATE]",
              "audio_slow": "[GENERATE]"
            },
            {
              "modifier_id": "mod_12_002",
              "modifier_source": "a little",
              "modifier_target": "[TRANSLATE]",
              "example_source": "I am a little tired.",
              "example_target": "[TRANSLATE]",
              "explanation_source": "'A little' softens the adjective; you're tired but not very tired.",
              "explanation_target": "[TRANSLATE]",
              "audio_normal": "[GENERATE]",
              "audio_slow": "[GENERATE]"
            }
          ]
        },
        "module_3_sentence_building": {
          "module_id": "module_3",
          "module_name": "Sentence Building",
          "module_code": "SENTENCE",
          "position_in_lesson": 3,
          "enabled": true,
          "required": true,
          "estimated_duration_seconds": 60,
          "title_source": "Build sentences",
          "title_target": "[TRANSLATE]",
          "module_type": "SentenceBuilding",
          "exercises": [
            {
              "exercise_id": "ex_sb_12_1",
              "target_sentence_source": "I am very tired.",
              "target_sentence_target": "[TRANSLATE]",
              "punctuation_mode": "auto_fit",
              "word_tiles": [
                {
                  "word_id": "w1",
                  "word_source": "I",
                  "word_target": "[TRANSLATE]",
                  "correct_position": 1
                },
                {
                  "word_id": "w2",
                  "word_source": "am",
                  "word_target": "[TRANSLATE]",
                  "correct_position": 2
                },
                {
                  "word_id": "w3",
                  "word_source": "very",
                  "word_target": "[TRANSLATE]",
                  "correct_position": 3
                },
                {
                  "word_id": "w4",
                  "word_source": "tired",
                  "word_target": "[TRANSLATE]",
                  "correct_position": 4
                }
              ],
              "hints_source": "Start with the speaker, then 'am', then the strength word, then the adjective.",
              "hints_target": "[TRANSLATE]",
              "exercise_type": "Drag-and-Drop Sentence Builder",
              "prompt_source": "Put the words in the correct order:",
              "prompt_target": "[TRANSLATE]"
            },
            {
              "exercise_id": "ex_sb_12_2",
              "target_sentence_source": "I am completely exhausted.",
              "target_sentence_target": "[TRANSLATE]",
              "punctuation_mode": "auto_fit",
              "word_tiles": [
                {
                  "word_id": "w1",
                  "word_source": "I",
                  "word_target": "[TRANSLATE]",
                  "correct_position": 1
                },
                {
                  "word_id": "w2",
                  "word_source": "am",
                  "word_target": "[TRANSLATE]",
                  "correct_position": 2
                },
                {
                  "word_id": "w3",
                  "word_source": "completely",
                  "word_target": "[TRANSLATE]",
                  "correct_position": 3
                },
                {
                  "word_id": "w4",
                  "word_source": "exhausted",
                  "word_target": "[TRANSLATE]",
                  "correct_position": 4
                }
              ],
              "hints_source": "Use a stronger adjective ('exhausted') with a stronger adverb ('completely').",
              "hints_target": "[TRANSLATE]",
              "exercise_type": "Drag-and-Drop Sentence Builder",
              "prompt_source": "Put the words in the correct order:",
              "prompt_target": "[TRANSLATE]"
            }
          ]
        },
        "module_dialogue_practice": {
          "module_id": "module_dialogue_practice",
          "module_name": "Dialogue Practice",
          "module_code": "DIALOGUE",
          "position_in_lesson": 4,
          "enabled": true,
          "required": true,
          "estimated_duration_seconds": 90,
          "title_source": "Conversation",
          "title_target": "[TRANSLATE]",
          "module_type": "Conversations",
          "setting_source": "A living room at the end of a long day.",
          "setting_target": "[TRANSLATE]",
          "context_source": "One person admits they're worn out and needs rest before dinner.",
          "context_target": "[TRANSLATE]",
          "setting": "A living room at the end of a long day.",
          "context": "One person admits they're worn out and needs rest before dinner.",
          "dialogue": [
            {
              "turn_id": "turn_001",
              "turn_number": 1,
              "speaker": "PARTNER",
              "text_source": "You look like you're about to fall asleep.",
              "text_target": "[TRANSLATE]",
              "audio_normal": "[GENERATE]",
              "audio_slow": "[GENERATE]",
              "practice_mode": "listen_and_repeat"
            },
            {
              "turn_id": "turn_002",
              "turn_number": 2,
              "speaker": "YOU",
              "text_source": "I am very tired.",
              "text_target": "[TRANSLATE]",
              "audio_normal": "[GENERATE]",
              "audio_slow": "[GENERATE]",
              "practice_mode": "speak_along"
            },
            {
              "turn_id": "turn_003",
              "turn_number": 3,
              "speaker": "PARTNER",
              "text_source": "Long day at work?",
              "text_target": "[TRANSLATE]",
              "audio_normal": "[GENERATE]",
              "audio_slow": "[GENERATE]",
              "practice_mode": "listen_and_repeat"
            },
            {
              "turn_id": "turn_004",
              "turn_number": 4,
              "speaker": "YOU",
              "text_source": "Yes, I have no energy left.",
              "text_target": "[TRANSLATE]",
              "audio_normal": "[GENERATE]",
              "audio_slow": "[GENERATE]",
              "practice_mode": "speak_along"
            },
            {
              "turn_id": "turn_005",
              "turn_number": 5,
              "speaker": "PARTNER",
              "text_source": "Go take a nap. Dinner can wait.",
              "text_target": "[TRANSLATE]",
              "audio_normal": "[GENERATE]",
              "audio_slow": "[GENERATE]",
              "practice_mode": "listen_and_repeat"
            }
          ]
        },
        "module_sprint_exercises": {
          "position_in_lesson": 5,
          "enabled": true,
          "required": true,
          "estimated_duration_seconds": 120,
          "title_source": "Quick practice",
          "title_target": "[TRANSLATE]",
          "randomize_order": true,
          "exercises": [
            {
              "exercise_id": "ex_v1_audio_image",
              "exercise_type": "Audio-to-Image Matching",
              "prompt_source": "Tap the image that matches what you hear:",
              "prompt_target": "[TRANSLATE]",
              "audio_stimulus": {
                "audio_file": "[GENERATE]",
                "play_on_load": true,
                "text_to_speak_target": "I am very tired."
              },
              "image_options": [
                {
                  "option_id": "opt_01",
                  "image_url": "",
                  "correct": true
                },
                {
                  "option_id": "opt_02",
                  "image_url": "",
                  "correct": false
                },
                {
                  "option_id": "opt_03",
                  "image_url": "",
                  "correct": false
                },
                {
                  "option_id": "opt_04",
                  "image_url": "",
                  "correct": false
                }
              ],
              "scoring": {
                "points_correct": 10,
                "points_incorrect": 0
              }
            },
            {
              "exercise_id": "ex_sp_flashcard",
              "exercise_type": "Digital Flashcards",
              "prompt_source": "Study the card:",
              "prompt_target": "[TRANSLATE]",
              "word": "tired",
              "definition": "Feeling that you need to rest or sleep.",
              "examples": [
                "I am very tired."
              ],
              "context": "Pairs with 'very', 'so', 'a little' to show different strengths of the feeling.",
              "word_source": "tired",
              "word_target": "[TRANSLATE]",
              "definition_source": "Feeling that you need to rest or sleep.",
              "definition_target": "[TRANSLATE]",
              "examples_source": [
                "I am very tired."
              ],
              "examples_target": [
                "[TRANSLATE]"
              ],
              "context_source": "Pairs with 'very', 'so', 'a little' to show different strengths of the feeling.",
              "context_target": "[TRANSLATE]",
              "scoring": {
                "points_correct": 5,
                "points_incorrect": 0
              }
            },
            {
              "exercise_id": "ex_sp_audio_blank",
              "exercise_type": "Audio Fill-in-the-Blank",
              "prompt_source": "Listen and complete:",
              "prompt_target": "[TRANSLATE]",
              "audio_stimulus": {
                "audio_file": "[GENERATE]",
                "play_on_load": true,
                "text_to_speak_target": "I am very tired."
              },
              "sentence": "I am very ___.",
              "sentence_source": "I am very ___.",
              "sentence_target": "[TRANSLATE]",
              "blanks": [
                4
              ],
              "correct_answer": "tired",
              "correct_answer_source": "tired",
              "correct_answer_target": "[TRANSLATE]",
              "scoring": {
                "points_correct": 10,
                "points_incorrect": 0
              }
            },
            {
              "exercise_id": "ex_sp_sentence_open",
              "exercise_type": "Sentence Completion (Open)",
              "prompt_source": "Finish in your own words:",
              "prompt_target": "[TRANSLATE]",
              "prompt": "Finish: 'I am very ___.'",
              "prompt_text_source": "Finish: 'I am very ___.'",
              "prompt_text_target": "[TRANSLATE]",
              "expected_response": "any feeling adjective (e.g. 'tired', 'sleepy', 'hungry', 'weary')",
              "expected_response_source": "any feeling adjective (e.g. 'tired', 'sleepy', 'hungry', 'weary')",
              "expected_response_target": "[TRANSLATE]",
              "scoring_criteria": "Accept any adjective describing how you feel.",
              "scoring_criteria_source": "Accept any adjective describing how you feel.",
              "scoring_criteria_target": "[TRANSLATE]",
              "scoring": {
                "points_correct": 10,
                "points_incorrect": 0
              }
            },
            {
              "exercise_id": "ex_sp_text_audio",
              "exercise_type": "Text-to-Audio Matching",
              "prompt_source": "Tap the audio that matches:",
              "prompt_target": "[TRANSLATE]",
              "text_stimulus": "exhausted",
              "text_stimulus_source": "exhausted",
              "text_stimulus_target": "[TRANSLATE]",
              "audio_options": [
                {
                  "option_id": "a1",
                  "audio_file": "[GENERATE]",
                  "text_to_speak_target": "exhausted",
                  "correct": true
                },
                {
                  "option_id": "a2",
                  "audio_file": "[GENERATE]",
                  "text_to_speak_target": "weary",
                  "correct": false
                }
              ],
              "correct_answer": "exhausted",
              "correct_answer_source": "exhausted",
              "correct_answer_target": "[TRANSLATE]",
              "scoring": {
                "points_correct": 10,
                "points_incorrect": 0
              }
            }
          ],
          "module_id": "module_sprint_exercises",
          "module_name": "Sprint & review",
          "module_code": "SPRINT",
          "module_type": "Review"
        }
      }
    },
    "translation_metadata": {
      "source_language": "en",
      "target_language": "RUNTIME_SELECTED",
      "translatable_field_patterns": [
        "**_target"
      ],
      "audio_generation_patterns": [
        "[GENERATE]",
        "[GENERATE_FOR_TARGET]"
      ]
    }
  },
  "metadata": {
    "lessonType": "malegado",
    "uploadSchema": "modules_canonical_v1",
    "convertedFrom": "new_structure_v4_phases",
    "sourcePath": "/home/metuge/Dev/submissions/malegado_new_structure/Dialogues/dialogue 33/lesson_12.json",
    "sourceLessonId": "badge_nap_future_001-L12"
  }
}
